LICENSE
MANIFEST.in
RELEASE-VERSION
setup.py
jquery_alchemy/__init__.py
jquery_alchemy.egg-info/PKG-INFO
jquery_alchemy.egg-info/SOURCES.txt
jquery_alchemy.egg-info/dependency_links.txt
jquery_alchemy.egg-info/requires.txt
jquery_alchemy.egg-info/top_level.txt