Metadata-Version: 1.0
Name: jquery-alchemy
Version: 0.0.7
Summary: A package which creates jquery_validation rules from sqlalchemy columns for use with web forms.
Home-page: http://www.github.com/mrichar1/jquery_alchemy
Author: Matthew Richardson.
Author-email: m.richardson@ed.ac.uk
License: GNU AGPL v3
Platform: UNKNOWN
Classifier: Development Status :: 4 - Beta
Classifier: License :: OSI Approved :: GNU Affero General Public License v3 or later (AGPLv3+)
Classifier: Programming Language :: Python :: 2.6
Classifier: Programming Language :: Python :: 3
